jupyter_openvscodeserver_proxy/__init__.py
jupyter_openvscodeserver_proxy/bin/openvscode-server.in
jupyter_openvscodeserver_proxy/icons/openvscode-server-logo.svg
jupyter_openvscodeserver_proxy-0.9.3.dist-info/LICENSE
jupyter_openvscodeserver_proxy-0.9.3.dist-info/METADATA
jupyter_openvscodeserver_proxy-0.9.3.dist-info/WHEEL
jupyter_openvscodeserver_proxy-0.9.3.dist-info/entry_points.txt
jupyter_openvscodeserver_proxy-0.9.3.dist-info/top_level.txt
jupyter_openvscodeserver_proxy-0.9.3.dist-info/RECORD
