Metadata-Version: 2.2
Name: jupyter-openvscodeserver-proxy
Version: 0.9.3
Summary: OpenVSCode-Server for JupyterLab
Home-page: https://github.com/FZJ-JSC/jupyter-openvscodeserver-proxy
Download-URL: https://github.com/FZJ-JSC/jupyter-openvscodeserver-proxy/archive/refs/tags/v0.9.3.tar.gz
Author: Jens Henrik Goebbert
Author-email: j.goebbert@fz-juelich.de
Keywords: jupyter,openvscode-server,jupyterhub,jupyter-server-proxy
Classifier: Programming Language :: Python :: 3
Classifier: License :: OSI Approved :: BSD License
Classifier: Operating System :: OS Independent
Classifier: Framework :: Jupyter
Requires-Python: >=3.6
License-File: LICENSE
Requires-Dist: jupyter-server-proxy>=3.2.3
Dynamic: author
Dynamic: author-email
Dynamic: classifier
Dynamic: description
Dynamic: description-content-type
Dynamic: download-url
Dynamic: home-page
Dynamic: keywords
Dynamic: requires-dist
Dynamic: requires-python
Dynamic: summary
